streamlit_card_select/__init__.py
streamlit_card_select/__version__.py
streamlit_card_select/component.py
streamlit_card_select/sample_app.py
streamlit_card_select/frontend/build/asset-manifest.json
streamlit_card_select/frontend/build/bootstrap.min.css
streamlit_card_select/frontend/build/index.html
streamlit_card_select/frontend/build/precache-manifest.ca184ffd88bae57e1a4dbaa625a01792.js
streamlit_card_select/frontend/build/service-worker.js
streamlit_card_select/frontend/build/static/js/2.c5dfe4cf.chunk.js
streamlit_card_select/frontend/build/static/js/2.c5dfe4cf.chunk.js.LICENSE.txt
streamlit_card_select/frontend/build/static/js/2.c5dfe4cf.chunk.js.map
streamlit_card_select/frontend/build/static/js/main.ffe65e8d.chunk.js
streamlit_card_select/frontend/build/static/js/main.ffe65e8d.chunk.js.map
streamlit_card_select/frontend/build/static/js/runtime-main.8d8cf6da.js
streamlit_card_select/frontend/build/static/js/runtime-main.8d8cf6da.js.map
streamlit_card_select-0.3.0.dist-info/LICENSE
streamlit_card_select-0.3.0.dist-info/METADATA
streamlit_card_select-0.3.0.dist-info/WHEEL
streamlit_card_select-0.3.0.dist-info/top_level.txt
streamlit_card_select-0.3.0.dist-info/RECORD
