Metadata-Version: 2.1
Name: streamlit-card-select
Version: 0.3.0
Summary: Streamlit component to select a card from a grid
Home-page: 
Author: Mirko Mälicke
Author-email: mirko@hydrocode.de
License: UNKNOWN
Platform: UNKNOWN
Requires-Python: >=3.6
License-File: LICENSE
Requires-Dist: streamlit (>=0.63)
